merge_pdf/__init__.py
merge_pdf/merge_pdf.py
mergemypdf-0.1.0.dist-info/LICENSE
mergemypdf-0.1.0.dist-info/METADATA
mergemypdf-0.1.0.dist-info/WHEEL
mergemypdf-0.1.0.dist-info/entry_points.txt
mergemypdf-0.1.0.dist-info/top_level.txt
mergemypdf-0.1.0.dist-info/RECORD
