Metadata-Version: 2.1
Name: mergemypdf
Version: 0.1.0
Summary: Merge Images and PDFs using CLI with customizations.
Home-page: https://github.com/kairavkkp/Merge-PDF
Author: kairavkkp
Author-email: kairavpithadia13@gmail.com
License: MIT
Keywords: Merge-pdf PDF-CLI merge pdf merge-pdf-local offline-merge pdf-merge jpg-pdf-merge image-pdf-merge png-jpg-merge-pdf
Platform: UNKNOWN
Classifier: Development Status :: 4 - Beta
Classifier: Programming Language :: Python :: 3
Classifier: Programming Language :: Python :: 3.5
Classifier: Programming Language :: Python :: 3.6
Classifier: Programming Language :: Python :: 3.7
Classifier: License :: OSI Approved :: MIT License
Classifier: Operating System :: Unix
Requires-Python: >=3.6
Requires-Dist: PyPDF2 (==1.26.0)
Requires-Dist: img2pdf (==0.4.0)
Requires-Dist: Pillow (==7.2.0)
